django_gssapi/__init__.py
django_gssapi/backends.py
django_gssapi/drf.py
django_gssapi/models.py
django_gssapi/urls.py
django_gssapi/utils.py
django_gssapi/views.py
django_gssapi-1.0.dist-info/COPYING
django_gssapi-1.0.dist-info/METADATA
django_gssapi-1.0.dist-info/WHEEL
django_gssapi-1.0.dist-info/top_level.txt
django_gssapi-1.0.dist-info/RECORD
