Metadata-Version: 2.1
Name: django-gssapi
Version: 1.0
Summary: GSSAPI authentication for Django
Home-page: http://dev.entrouvert.org/projects/django-gssapi/
Author: Entr'ouvert
Author-email: info@entrouvert.org
Maintainer: Benjamin Dauvergne
Maintainer-email: bdauvergne@entrouvert.com
License: AGPLv3 or later
Platform: UNKNOWN
Requires-Dist: django (>1.8)
Requires-Dist: gssapi
Requires-Dist: six
